[
    {
        "id": "1TDS",
        "nome": "1º TDS",
        "estudantes": [
    {"matricula": "3875260", "nome_completo": "ALISSON MATHEUS NUNES DA SILVA", "telefone": "5581986896717", "email": "alisson.matheusnunes10@gmail.com"},
    {"matricula": "3873141", "nome_completo": "ANA KAROLLAYNE ALBINO ARAUJO DA SILVA", "telefone": "5581991452355", "email": "Karollayneana65@gmail.com"},
    {"matricula": "3873777", "nome_completo": "ANA LUIZA LOPES DE CARVALHO", "telefone": "5581996167495", "email": "luiza.ana.lopes10@gmail.com"},
    {"matricula": "3869519", "nome_completo": "ANDRE LINS DE OLIVEIRA", "telefone": "5581989258086", "email": "andre07lins@gmail.com"},
    {"matricula": "3869503", "nome_completo": "ANDRE VINICIUS DA SILVA DIAS", "telefone": "5581992440974", "email": "andre2002vini@gmail.com"},
    {"matricula": "3873897", "nome_completo": "BIANCA VICTORIA AUGUSTA ZEFERINO DA SILVA", "telefone": "5581996043258", "email": "biancavictoria1122@gmail.com"},
    {"matricula": "3882664", "nome_completo": "BRUNNA RAPHAELLA MARQUES RODRIGUES", "telefone": "5581991868493", "email": "brunnaraphaella27032009@gmail.com"},
    {"matricula": "SEM MAT", "nome_completo": "DAVI UCHOA DE MELO", "telefone": "5581991296955", "email": "daviuchoa62@gmail.com"},
    {"matricula": "3882660", "nome_completo": "ERICK EUNA GOMES DA SILVA", "telefone": "5581991921743", "email": "erick.egsilva@aluno.educacao.pe.gov.br"},
    {"matricula": "3873804", "nome_completo": "GABRIEL MACARIO DE OLIVEIRA", "telefone": "5581999089677", "email": "sgabrielmacario45@gmail.com"},
    {"matricula": "3873974", "nome_completo": "GLEYDSON GUILHERME SILVA MELO", "telefone": "5581985667698", "email": "gleydsonescola01@gmail.com"},
    {"matricula": "3757714", "nome_completo": "GUILHERME FILIPE ALVES SILVA", "telefone": "5581992162682", "email": "guifilipi42@gmail.com"},
    {"matricula": "3869578", "nome_completo": "IONAN MARTINS SILVA DE ALMEIDA", "telefone": "5581994254954", "email": "ionanalmeida2@gmail.com"},
    {"matricula": "3869525", "nome_completo": "ISAAC RYHAN IZIDORO CAMPOS", "telefone": "5581993358900", "email": "gs4004090@gmail.com"},
    {"matricula": "3875543", "nome_completo": "JACIELY CIBELE VICENTE DA SILVA", "telefone": "5581991749034", "email": "Jocielmajaciely@gmail.com"},
    {"matricula": "3873420", "nome_completo": "JAEMILY DA SILVA SANTOS", "telefone": "5581989116497", "email": "jaemilydasilvasantos@gmail.com"},
    {"matricula": "3875333", "nome_completo": "JHONATTA KAUHAN LOPES DA SILVA", "telefone": "5581993530908", "email": "Jhonattakauhanlopes@gmail.com"},
    {"matricula": "3869759", "nome_completo": "JOAO ARTUR DE BARROS FERREIRA", "telefone": "5581971042279", "email": "joaoarturf34@gmail.com"},
    {"matricula": "3758977", "nome_completo": "JOÃO VYTOR GOMES DASILVA", "telefone": "5581981000087", "email": "vytor331@gmail.com"},
    {"matricula": "3873582", "nome_completo": "JORGE LUIZ DA ROCHA NETO", "telefone": "5581982269692", "email": "jorgerocha020908@gmail.com"},
    {"matricula": "3874094", "nome_completo": "JULIA BEATRIZ DE OLIVEIRA", "telefone": "5581996107092", "email": "ffsjujuh@gmail.com"},
    {"matricula": "3874179", "nome_completo": "LAVINIA CECILIA DE OLIVEIRA DA SILVA", "telefone": "5581973176395", "email": "Laviniacecilia99@gmail.com"},
    {"matricula": "3869418", "nome_completo": "LETICIA GABRIELLY DA SILVA GERMANO", "telefone": "5581993330679", "email": "leticiaggermano0@gmail.com"},
    {"matricula": "3875565", "nome_completo": "LIVIA GABRIELLY RODRIGUES COSTA FIRMINO", "telefone": "5581985346159", "email": "Firminolivia70@gmail.com"},
    {"matricula": "3875464", "nome_completo": "MARCOS MANOEL CARNEIRO ALVES BEZERRA", "telefone": "5581993301581", "email": "Marcosmanoelbezerra03@gmail.com"},
    {"matricula": "3869571", "nome_completo": "MARIA LUIZA DE LIMA SILVA", "telefone": "5581996978075", "email": "ml8290060@gmail.com"},
    {"matricula": "3873984", "nome_completo": "MARIA TAYARA ALESSANDRA GOMES DA SILVA", "telefone": "5581997100226", "email": "Tayaragomes620@gmail.com"},
    {"matricula": "3671104", "nome_completo": "MARIA VITORIA FERREIRA SERAFIM", "telefone": "5581973360837", "email": "valcleideferreira243@gmail.com"},
    {"matricula": "3874622", "nome_completo": "MARIANY MACIEL ALEIXO", "telefone": "5581996499915", "email": "Marianymaciel071@gmail.com"},
    {"matricula": "3869645", "nome_completo": "MAYCON VINICIUS PEREIRA DA COSTA", "telefone": "5581973013687", "email": "Maycon22haj@gmail.com"},
    {"matricula": "3875577", "nome_completo": "MURYLLO KENNEDY FERREIRA PELLEGRINO", "telefone": "5581992104734", "email": "muryllokennedy45@gmail.com"},
    {"matricula": "3862642", "nome_completo": "NATHALLY SILVA SOUSA", "telefone": "5581998082201", "email": "nathallys410@gmail.com"},
    {"matricula": "3420598", "nome_completo": "PAULO VICTOR FAUSTINO SERCUNDES DE LIRA", "telefone": "5581999084270", "email": "vittindugrau0987@gmail.com"},
    {"matricula": "3873602", "nome_completo": "RAELLY MARIA DA SILVA", "telefone": "5581994789455", "email": "Raellymaria2010@gmail.com"},
    {"matricula": "3873305", "nome_completo": "RENAN SILVA DE CARVALHO", "telefone": "5581993168623", "email": "renanprfalunoetepalmares@gmail.com"},
    {"matricula": "3873554", "nome_completo": "SAMUEL SANTANA DA SILVA", "telefone": "5581999709003", "email": "santana123samuelz@gmail.com"},
    {"matricula": "3873486", "nome_completo": "WERYKA CAMYLLY DOS SANTOS GOMES", "telefone": "5581973331606", "email": "werykagomez677@gmail.com"},
    {"matricula": "3875228", "nome_completo": "WEVERTTON GABRIEL FLORENCIO CAVALCANTI", "telefone": "5581989028366", "email": "Duduw606@gmail.com"}
]
    },
    {
        "id": "2TDSA",
        "nome": "2º TDS-A",
        "estudantes": [
    {"matricula": "3675509", "nome_completo": "ALESSANDRO BRAZ DE MACEDO SILVA", "telefone": "5581994585406", "email": "alessandrobraz2000@gmail.com"},
    {"matricula": "3671350", "nome_completo": "ALINE VITORIA RAMOS DA SILVA", "telefone": "5581993073248", "email": "aline.vrsilva50@aluno.educacao.pe.gov.br"},
    {"matricula": "3674995", "nome_completo": "ALLANA KATIELY NUNES DOS SANTOS", "telefone": "5581989175017", "email": "allanarebeca@gmail.com"},
    {"matricula": "3686684", "nome_completo": "ANDRE MACARIO DOS SANTOS JUNIOR", "telefone": "5581996459356", "email": "andremacario14@gmail.com"},
    {"matricula": "3675239", "nome_completo": "BRUNA BEATRIZ MARIA DE SOUZA", "telefone": "5581973464072", "email": "beatrizbruna615@gmail.com"},
    {"matricula": "3618996", "nome_completo": "CAUA FELIPE SOARES VIRTUOZO", "telefone": "5581981014864", "email": "cauafelipe942@gmail.com"},
    {"matricula": "3642415", "nome_completo": "CHARLYS LUCAS SILVA DE OLIVEIRA", "telefone": "5581992885586", "email": "charlyslucas26@gmail.com"},
    {"matricula": "3675484", "nome_completo": "DEBORAH PATRYCIA DA SILVA MORAES", "telefone": "5581996887460", "email": "debyy2008@gmail.com"},
    {"matricula": "3674957", "nome_completo": "ELLICE CAROLINE S. CALAZANS DOS SANTOS", "telefone": "5581998797131", "email": "ellicecaroline0@gmail.com"},
    {"matricula": "3675439", "nome_completo": "GABRIEL VITAL DA SILVA", "telefone": "5581989544121", "email": "gabriel.vsilva439@aluno.educacao.pe.gov.br"},
    {"matricula": "3621079", "nome_completo": "GEORGIA MARIA M. DE MELO F. DE LIMA", "telefone": "5581991711604", "email": "Georgiamaria232@gmail.com"},
    {"matricula": "3671280", "nome_completo": "ISABELLA CRISTINA CAVALCANTI PIO", "telefone": "5581981650061", "email": "isabellacavalcanti941@gmail.com"},
    {"matricula": "3675228", "nome_completo": "ISABELLY MAYSA SANTANA DE SOUZA", "telefone": "5581996868598", "email": "isabelly.mssouza@aluno.educacao.pe.gov.br"},
    {"matricula": "3675412", "nome_completo": "IZABELLA ISCALABRINE FERREIRA LIMA", "telefone": "5581997329296", "email": "iscalabrineizabella@gmail.com"},
    {"matricula": "3677439", "nome_completo": "JAMILLY MARIANE LUCENA MARTINS", "telefone": "5581989847257", "email": "marianejamilly0@gmail.com"},
    {"matricula": "3671340", "nome_completo": "JAYRO FELIPE NASCIMENTO DA SILVA", "telefone": "5581984775581", "email": "jayrofsilva@gmail.com"},
    {"matricula": "3674986", "nome_completo": "JOAO PEDRO ALVES BEZERRA", "telefone": "5581979049161", "email": "joaopedroalvesbezerra@gmail.com"},
    {"matricula": "3671117", "nome_completo": "JOHN MACLEBIO MELO DA SILVA", "telefone": "5581985155686", "email": "dkzada2067@gmail.com"},
    {"matricula": "3671110", "nome_completo": "JONAS FRANCISCO FERREIRA DE ASSIS", "telefone": "5581998995400", "email": "onasfrancisco201@gmail.com"},
    {"matricula": "3675153", "nome_completo": "JOSE MARQUES DE ALMEIDA", "telefone": "5581981464192", "email": "ajosemarques010@gmail.com"},
    {"matricula": "3671075", "nome_completo": "KAUA VICTOR CABRAL NASCIMENTO DA SILVA", "telefone": "5581992826335", "email": "Vkaua7251@gmail.com"},
    {"matricula": "3674926", "nome_completo": "LUIZ PAULO DA SILVA MELO", "telefone": "5581992282511", "email": "luizpaulo201909@gmail.com"},
    {"matricula": "3677435", "nome_completo": "LUIZA FERNANDA DE OLIVEIRA NASCIMENTO", "telefone": "5581997087837", "email": "fernandaluiza027@gmail.com"},
    {"matricula": "3676614", "nome_completo": "MARIA FRANCIELY DA SILVA", "telefone": "5581999698391", "email": "mfrancielyete@gmail.com"},
    {"matricula": "3675512", "nome_completo": "NICOLY EDUARDA GAUBERTO CASTRO DE LIMA", "telefone": "5581999825764", "email": "Nicolyeduanda@gmail.com"},
    {"matricula": "3675498", "nome_completo": "PAULO MAYKON DE MOURA SILVA", "telefone": "5581985832533", "email": "paulomaykonmoura@gmail.com"},
    {"matricula": "3676611", "nome_completo": "RAUAN NILLO MACARIO DA SILVA MOURA", "telefone": "5581999547758", "email": "Rauannillomacariodasilvamoura@gmail.com"},
    {"matricula": "3671593", "nome_completo": "REBECA VITORIA DIAS DA SILVA", "telefone": "5581973009688", "email": "allanarebeca@gmail.com"},
    {"matricula": "3677792", "nome_completo": "RITA DE CASSIA DE FRANCA AMORIM", "telefone": "5581992873866", "email": "cassiaritabts@gmail.com"},
    {"matricula": "3674914", "nome_completo": "SARA BEATRIZ FERREIRA DA SILVA", "telefone": "5581999791441", "email": "sarab8472@gmail.com"},
    {"matricula": "3675039", "nome_completo": "YASMIN THAUANY SILVA LEAO", "telefone": "5581998338370", "email": "Yasminthauany782@gmail.com"}
]
    },
    {
        "id": "2TDSB",
        "nome": "2º TDS-B",
        "estudantes": [
    {"matricula": "3874625", "nome_completo": "ANNY BEATRIZ SILVA FERREIRA", "telefone": "5581994397868", "email": "anny.bsferreira@aluno.educacao.pe.gov.br"},
    {"matricula": "3875260", "nome_completo": "AYSLLAN KELVE ARAUJO DA SILVA", "telefone": "5581995089435", "email": "kelvearaujo14@gmail.com"},
    {"matricula": "3873141", "nome_completo": "CAMILA MANUELA SOARES DA SILVA", "telefone": "5581981852831", "email": "camilamanuelacami1@gmail.com"},
    {"matricula": "3873777", "nome_completo": "CAUA VINICIUS SANTOS RIBEIRO", "telefone": "5581974002916", "email": "NÃO CADASTRADO"},
    {"matricula": "3869503", "nome_completo": "ELOA CAROLINA FARIAS VIEIRA SANTOS", "telefone": "5581989230567", "email": "eloacarolina585@gmail.com"},
    {"matricula": "3873897", "nome_completo": "EROS VINICIUS ALVES DOS SANTOS SILVA", "telefone": "5581992711848", "email": "erosvinicius424@gmail.com"},
    {"matricula": "3882664", "nome_completo": "GABRIEL ARTHUR GARCIA MACIEL", "telefone": "5581999037940", "email": "Gabriel.arthur.gacia.maciel@gmail.com"},
    {"matricula": "3891869", "nome_completo": "JOSE HELENO ANTONIO DA SILVA JUNIOR", "telefone": "5581993125586", "email": "jose.hasjunior@aluno.educacao.pe.gov.br"},
    {"matricula": null, "nome_completo": "JULIO GABRIEL GONZAGA DE OLIVEIRA", "telefone": "5581996695505", "email": "julho.gonzaguinha@gmail.com"},
    {"matricula": "3882660", "nome_completo": "KAIO EMANOEL DA SILVA COSTA", "telefone": "5581996121102", "email": "Kaioemanoel.ap@gmail.com"},
    {"matricula": "3873804", "nome_completo": "KASSIANE CARLA BARBOSA SILVA", "telefone": "5581981289544", "email": "kassianecarla1722@gmail.com"},
    {"matricula": "3873974", "nome_completo": "LAVINIA MARIA DE LIMA", "telefone": "5581993860133", "email": "lavinialima20089@gmail.com"},
    {"matricula": "3757714", "nome_completo": "LUCAS HENRIQUE DOS SANTOS SILVA", "telefone": "5581992721141", "email": "lucas.hssilva@aluno.educacao.pe.gov.br"},
    {"matricula": "3869578", "nome_completo": "MARCELO FERREIRA DELFINO DO CARMO FILHO", "telefone": "5581987676682", "email": "marcelodelfi08@gmail.com"},
    {"matricula": "3869525", "nome_completo": "MARCOS ANDRE LIMA DE OLIVEIRA", "telefone": "5581999179786", "email": "Limamarcosandrei@gmail.com"},
    {"matricula": "3875543", "nome_completo": "MARIA EDUARDA DOMINGOS MARTINS", "telefone": "5581992184415", "email": "martins27.duda@gmail.com"},
    {"matricula": "3873420", "nome_completo": "MARIA ESTELA SILVA DE AZEVEDO", "telefone": "5581971053427", "email": "maria.esazevedo27@aluno.educacao.pe.gov.br"},
    {"matricula": "3875333", "nome_completo": "PAULO HENRIQUE FIRMINO DIAS", "telefone": "5581920003711", "email": "paulo.hfdias@aluno.educacao.pe.gov.br"},
    {"matricula": "3869759", "nome_completo": "PEDRO LEONARDO DA SILVA SANTOS", "telefone": "5581994763409", "email": "pedroleonardo1890@gmail.com"},
    {"matricula": "3758977", "nome_completo": "SAMMIRA JOANA RAMOS VIANA", "telefone": "5581996018432", "email": "Samviana2008@gmail.com"},
    {"matricula": "3873582", "nome_completo": "SARAH LAYS NASCIMENTO CAVALCANTI", "telefone": "5581997389666", "email": "layssarah2@gmail.com"},
    {"matricula": "3874094", "nome_completo": "SAULO GALDINO DA SILVA", "telefone": "5581989601430", "email": "saulosilva2009x7@gmail.com"},
    {"matricula": "3874179", "nome_completo": "VINICIUS GABRIEL CAVALCANTE OLIVEIRA DE ALBUQUERQUE", "telefone": "5581999790914", "email": "viniciucavalcante1708@gmail.com"},
    {"matricula": "3869418", "nome_completo": "VITAL GABRIEL DE OLIVEIRA SOUZA", "telefone": "5581999886620", "email": "vxgab93@gmail.com"},
    {"matricula": "3875565", "nome_completo": "VITOR MANOEL SANTOS DA SILVA", "telefone": "5581994026071", "email": "vmsds8990@gmail.com"},
    {"matricula": "3875464", "nome_completo": "YEDA VITORIA SILVA AGRELI DOS SANTO", "telefone": "5581993997254", "email": "hikarikkilefty@gmail.com"}
]
    }
]